{
  "meta": {
    "title": "Traffic Challan Assistance & Settlement Support | ChallanSetu",
    "description": "Get expert challan assistance for Delhi NCR. Submit your vehicle details and our team helps with settlement support. Savings up to 50% on eligible challans. Zero convenience fee.",
    "keywords": ["challan", "traffic challan", "vehicle challan", "pay challan online", "echallan", "challan settlement", "Delhi challan", "Noida challan", "Gurgaon challan", "Ghaziabad challan"]
  },
  "siteUrl": "https://challansetu.com",
  "siteName": "ChallanSetu",
  "footer": {
    "copyright": "ChallanSetu",
    "tagline": "Zero convenience fee. Savings up to 50% based on challan details. Transparent and honest."
  },
  "contact": {
    "email": "challansetu@gmail.com",
    "supportHours": "Mon–Sat, 9am–6pm IST",
    "responseTime": "We respond within 4 business hours"
  },
  "serviceArea": ["Delhi", "Noida", "Gurgaon", "Ghaziabad"]
}
